polygone_nms/__init__.py
polygone_nms/nms.py
polygone_nms/utils.py
polygonenms_ofo_fork-0.1.0.dist-info/LICENSE
polygonenms_ofo_fork-0.1.0.dist-info/METADATA
polygonenms_ofo_fork-0.1.0.dist-info/WHEEL
polygonenms_ofo_fork-0.1.0.dist-info/RECORD
