Metadata-Version: 2.3
Name: polygonenms-ofo-fork
Version: 0.1.0
Summary: PolyGoneNMS with updated dependency versions
License: MIT
Author: Vladimir Zaigrajew
Author-email: vladimirzaigrajew@gmail.com
Requires-Python: >=3.10,<3.12
Classifier: License :: OSI Approved :: MIT License
Classifier: Programming Language :: Python :: 3
Classifier: Programming Language :: Python :: 3.10
Classifier: Programming Language :: Python :: 3.11
Requires-Dist: numpy (>=2.2.1)
Requires-Dist: rtree (>=1.0.1)
Requires-Dist: shapely (>=2.0.0)
